molosp/__init__.py
molosp/loader.py
molosp/logger.py
molosp-0.1.1.dist-info/licenses/LICENSE
molosp-0.1.1.dist-info/METADATA
molosp-0.1.1.dist-info/WHEEL
molosp-0.1.1.dist-info/top_level.txt
molosp-0.1.1.dist-info/RECORD
