Metadata-Version: 2.4
Name: molosp
Version: 0.1.1
Summary: MOdule LOader for SPark
License: MIT License
Requires-Python: >=3.8
License-File: LICENSE
Requires-Dist: boto3
Provides-Extra: dev
Requires-Dist: pytest; extra == "dev"
Dynamic: license-file
